torchTextClassifiers/__init__.py
torchTextClassifiers/dataset/__init__.py
torchTextClassifiers/dataset/dataset.py
torchTextClassifiers/model/__init__.py
torchTextClassifiers/model/components/__init__.py
torchTextClassifiers/model/components/attention.py
torchTextClassifiers/model/components/categorical_var_net.py
torchTextClassifiers/model/components/classification_head.py
torchTextClassifiers/model/components/text_embedder.py
torchTextClassifiers/model/lightning.py
torchTextClassifiers/model/model.py
torchTextClassifiers/tokenizers/WordPiece.py
torchTextClassifiers/tokenizers/__init__.py
torchTextClassifiers/tokenizers/base.py
torchTextClassifiers/tokenizers/ngram.py
torchTextClassifiers/torchTextClassifiers.py
torchTextClassifiers/utilities/__init__.py
torchTextClassifiers/utilities/plot_explainability.py
torchtextclassifiers-1.0.3.dist-info/WHEEL
torchtextclassifiers-1.0.3.dist-info/METADATA
torchtextclassifiers-1.0.3.dist-info/RECORD
