Metadata-Version: 2.3
Name: torchtextclassifiers
Version: 1.0.3
Summary: A text classification toolkit to easily build, train and evaluate deep learning text classifiers using PyTorch.
Keywords: fastText,text classification,NLP,automatic coding,deep learning
Author: Cédric Couralet, Meilame Tayebjee
Author-email: Cédric Couralet <cedric.couralet@insee.fr>, Meilame Tayebjee <meilame.tayebjee@insee.fr>
Classifier: Programming Language :: Python :: 3
Classifier: License :: OSI Approved :: MIT License
Classifier: Operating System :: OS Independent
Requires-Dist: numpy>=1.26.4
Requires-Dist: pytorch-lightning>=2.4.0
Requires-Dist: unidecode ; extra == 'explainability'
Requires-Dist: nltk ; extra == 'explainability'
Requires-Dist: captum ; extra == 'explainability'
Requires-Dist: tokenizers>=0.22.1 ; extra == 'huggingface'
Requires-Dist: transformers>=4.57.1 ; extra == 'huggingface'
Requires-Dist: datasets>=4.3.0 ; extra == 'huggingface'
Requires-Dist: unidecode ; extra == 'preprocess'
Requires-Dist: nltk ; extra == 'preprocess'
Requires-Python: >=3.11
Provides-Extra: explainability
Provides-Extra: huggingface
Provides-Extra: preprocess
